{
  "stem": "nj_backup_20260530_153133",
  "reason": "manual",
  "created_iso": "2026-05-30T15:31:33+05:30",
  "db_bytes": 14151680,
  "rows": {
    "app_config": 1,
    "quotations": 1,
    "warranty_certificates": 3
  },
  "sha256": {
    "db": "50736f0364346f56e6d051a6ae1461767bc753bf346ea353c0a32d5abb0f3cc3",
    "json": "f8d6d038702548dffa03c21311829dea41c543cfbd83485b3382c31616643bae"
  },
  "verify": {
    "db_integrity": "ok",
    "db_hash_match": true,
    "json_parse": true
  },
  "targets": {},
  "ok": false
}